README.rst
setup.py
consent_user_information/__init__.py
consent_user_information/admin.py
consent_user_information/apps.py
consent_user_information/compat.py
consent_user_information/conf.py
consent_user_information/middleware.py
consent_user_information/models.py
consent_user_information/utils.py
consent_user_information/views.py
consent_user_information/migrations/0001_initial.py
consent_user_information/migrations/0002_consentuserinformation_os.py
consent_user_information/migrations/__init__.py
django_consent_user_information.egg-info/PKG-INFO
django_consent_user_information.egg-info/SOURCES.txt
django_consent_user_information.egg-info/dependency_links.txt
django_consent_user_information.egg-info/entry_points.txt
django_consent_user_information.egg-info/requires.txt
django_consent_user_information.egg-info/top_level.txt
tests/__init__.py
tests/conftest.py
tests/forms.py
tests/settings.py
tests/test_utils.py
tests/test_views.py
tests/urls.py
tests/views.py