Metadata-Version: 1.1
Name: django-consent-user-information
Version: 0.4
Summary: To store information about the user.
Home-page: https://github.com/hobbestigrou/django-consent-user-information
Author: Hobbestigrou
Author-email: hobbestigrou@erakis.eu
License: MIT
Keywords: django,consent
Platform: UNKNOWN
Classifier: Development Status :: 4 - Beta
Classifier: Intended Audience :: Developers
Classifier: License :: OSI Approved :: MIT License
Classifier: Natural Language :: English
Classifier: Operating System :: Unix
Classifier: Programming Language :: Python :: 2.7
Classifier: Programming Language :: Python :: 3.4
Classifier: Programming Language :: Python :: Implementation :: PyPy
Classifier: Operating System :: OS Independent
